{
  "project_info": {
    "project_number": "569164141454",
    "firebase_url": "https://hubble-home.firebaseio.com",
    "project_id": "hubble-home",
    "storage_bucket": "hubble-home.appspot.com"
  },
  "client": [
    {
      "client_info": {
        "mobilesdk_app_id": "1:569164141454:android:1cd632ee86f82295",
        "android_client_info": {
          "package_name": "com.hubbleconnected.camera"
        }
      },
      "oauth_client": [
        {
          "client_id": "569164141454-1jb1q0qu25c6j01pompq6fhind2dr6hc.apps.googleusercontent.com",
          "client_type": 3
        }
      ],
      "api_key": [
        {
          "current_key": "AIzaSyA5beQoiw7ypgt16tlut07K2FFDAoCiNg4"
        }
      ],
      "services": {
        "analytics_service": {
          "status": 1
        },
        "appinvite_service": {
          "status": 1,
          "other_platform_oauth_client": []
        },
        "ads_service": {
          "status": 2
        }
      }
    }
  ],
  "configuration_version": "1"
}